sample/__init__.py
sample/package_data.dat
sample/simple.py
utils/ReWiCreateString.py
utils/ReWiFilesHandle.py
utils/__init__.py
utils/binHandler.py
utils/binHandlers.py
utils/bytesHelper.py
utils/checksum.py
utils/common.py
utils/configsDefault.py
utils/configsHandler.py
utils/coordsHelper.py
utils/csvHandler.py
utils/datasHandler.py
utils/debugHelper.py
utils/filePathHelper.py
utils/filesHandlers.py
utils/filesHelper.py
utils/instructionHandlers.py
utils/logsRecorder.py
utils/picturesHandler.py
utils/refactorPyCode.py
utils/resourcesCodeFix.py
utils/sqlite3Handler.py
utils/sqlite3Handlers.py
utils/strHandlers.py
utils/strHelper.py
utils/typeHelper.py
utils/utilsExample.py
PyKitReWi-0.0.4.dist-info/METADATA
PyKitReWi-0.0.4.dist-info/WHEEL
PyKitReWi-0.0.4.dist-info/entry_points.txt
PyKitReWi-0.0.4.dist-info/top_level.txt
PyKitReWi-0.0.4.dist-info/RECORD
